calculator/__init__.py
calculator/ex8.py
TestSimpleCalculatorWilliamfleith-0.0.1.dist-info/METADATA
TestSimpleCalculatorWilliamfleith-0.0.1.dist-info/WHEEL
TestSimpleCalculatorWilliamfleith-0.0.1.dist-info/top_level.txt
TestSimpleCalculatorWilliamfleith-0.0.1.dist-info/RECORD
